{"stats":{"minecraft:mined":{"securitycraft:mine":1,"minecraft:spruce_planks":16,"meadow:alpine_salt_ore":9,"minecraft:white_bed":3,"butcher:skinned_cow_corpse":1,"tconstruct:tinker_station":1,"vinery:dark_cherry_leaves":3,"botania:red_mystical_flower":1,"butcher:pigcorpse":3,"minecraft:grass_block":361,"meadow:pine_log":23,"minecraft:jungle_log":1,"butcher:sheephead":2,"butcher:chicken_corpse_skinned":1,"meadow:pine_planks":2,"minecraft:tall_seagrass":1,"butcher:deepslatesulfurore":3,"minecraft:fire":68,"minecraft:iron_ore":50,"minecraft:cobbled_deepslate":2,"tconstruct:cobalt_ore":2,"minecraft:pumpkin":2,"minecraft:skeleton_wall_skull":1,"minecraft:iron_bars":9,"botania:brown_mystical_flower":1,"butcher:hangingzombie":1,"minecraft:blackstone":13,"minecraft:kelp_plant":3,"butcher:sheepcorpse":2,"vinery:red_grape_bush":3,"tconstruct:greenheart_log":5,"minecraft:creeper_wall_head":2,"minecraft:cobblestone":24,"butcher:pillagercorpseclothed":1,"minecraft:sugar_cane":4,"minecraft:wall_torch":2,"minecraft:pink_petals":1,"farmersdelight:sandy_shrub":5,"meadow:pine_leaves_2":11,"butcher:bloodgratetank":4,"minecraft:birch_log":6,"butcher:sulfurore":3,"minecraft:orange_tulip":1,"minecraft:stone_brick_stairs":1,"meadow:limestone":27,"minecraft:grass":182,"botania:gray_mushroom":1,"minecraft:oak_log":36,"minecraft:dirt":44,"minecraft:smooth_basalt":1,"vinery:apple_leaves":1,"minecraft:netherrack":7,"minecraft:oak_leaves":78,"minecraft:deepslate":10,"minecraft:tuff":14,"meadow:small_fir":2,"minecraft:mossy_cobblestone":3,"butcher:pillagerhead":2,"minecraft:deepslate_diamond_ore":32,"butcher:hanging_chicken_skinned_corpse":1,"farmersdelight:wild_carrots":4,"butcher:cow_headf":2,"farmersdelight:wild_cabbages":8,"minecraft:spruce_leaves":9,"butcher:pighead":1,"minecraft:rooted_dirt":1,"minecraft:hay_block":7,"minecraft:large_fern":3,"minecraft:furnace":6,"minecraft:andesite":6,"meadow:fire_lily":2,"treechop:chopped_log":15,"meadow:eriophorum":13,"farmersdelight:rope":5,"minecraft:deepslate_iron_ore":18,"minecraft:vine":1,"vinery:grapevine_stem":4,"meadow:pine_leaves":4,"minecraft:stone":156,"tconstruct:earth_congealed_slime":6,"meadow:pine_sapling":3,"minecraft:podzol":3,"botania:lime_mystical_flower":7,"vinery:dark_cherry_log":5,"botania:lime_mushroom":1,"minecraft:crafting_table":5,"botania:yellow_double_flower":1,"meadow:alpine_coal_ore":1,"butcher:chicken_corpse":2,"minecraft:tall_grass":74,"butcher:zombie":7,"meadow:pine_fence":1,"botania:cyan_mystical_flower":3,"butcher:drained_hanging_cow":1,"minecraft:coarse_dirt":2,"minecraft:spruce_log":7,"butcher:hook_block":8,"minecraft:birch_leaves":1,"minecraft:coal_ore":29,"butcher:pillager":1,"minecraft:cherry_leaves":5,"meadow:enzian":10,"minecraft:gravel":4,"meadow:cobbled_limestone":4,"meadow:alpine_iron_ore":2,"minecraft:fern":13},"minecraft:killed":{"minecraft:spider":9,"minecraft:skeleton":9,"minecraft:bee":1,"minecraft:pig":7,"minecraft:creeper":5,"minecraft:sheep":6,"minecraft:zombie":24,"minecraft:donkey":2,"meadow:wooly_cow":1,"minecraft:cow":3,"minecraft:drowned":1},"minecraft:killed_by":{"minecraft:creeper":2,"minecraft:cave_spider":1,"minecraft:zombie":2,"minecraft:enderman":1,"minecraft:skeleton":6},"minecraft:picked_up":{"vinery:red_grape":7,"minecraft:wheat":4,"securitycraft:keypad_item":1,"minecraft:creeper_head":5,"vinery:red_grape_seeds":2,"butcher:raw_pork_shoulder":4,"minecraft:stone_brick_stairs":1,"butcher:skeletoncorpse":1,"butcher:cowcorpseitem":2,"minecraft:string":15,"butcher:bloodgratetank":4,"butcher:clothed_pillager_corpse":2,"minecraft:zombie_head":3,"minecraft:spruce_planks":15,"minecraft:cobbled_deepslate":12,"meadow:enzian":10,"farmersdelight:cabbage":2,"butcher:chicken_drained_corpse_item":2,"butcher:skinned_cow_corpse_item":2,"butcher:pillagerdisguise_leggings":1,"farmersdelight:cabbage_seeds":9,"minecraft:furnace":6,"minecraft:golden_helmet":1,"minecraft:stick":59,"minecraft:torch":6,"minecraft:porkchop":21,"minecraft:cherry_log":1,"butcher:raw_pork_leg":4,"minecraft:rotten_flesh":42,"butcher:chicken_corpse_item":5,"farmersdelight:rope":5,"butcher:raw_pork_belly":4,"butcher:pillagermeat":6,"vinery:dark_cherry_log":5,"minecraft:iron_bars":9,"minecraft:cobblestone":194,"butcher:creepercarcass":5,"minecraft:birch_log":14,"minecraft:pink_petals":5,"butcher:pig_corpse_item":8,"tconstruct:greenheart_log":5,"minecraft:andesite":6,"butcher:pillagercorpse":1,"minecraft:tuff":14,"butcher:kidney":32,"farmersdelight:tomato":6,"minecraft:dirt":537,"securitycraft:reinforced_stone_button":8,"minecraft:bone":62,"butcher:cow_skin":4,"butcher:raw_ribeye_steak":2,"botania:cyan_mystical_flower":3,"minecraft:orange_tulip":1,"minecraft:wheat_seeds":49,"butcher:raw_tbone_steak":2,"butcher:animalfat":50,"botania:gray_mushroom":1,"butcher:intestines":16,"butcher:stomach":16,"vinery:grapevine_stem":4,"meadow:cobbled_limestone":31,"minecraft:glowstone_dust":3,"minecraft:oak_planks":1,"butcher:cow_headf":4,"botania:red_mystical_flower":1,"securitycraft:mine":1,"patchouli:guide_book":1,"botania:yellow_double_flower":1,"butcher:raw_pork_ham":4,"minecraft:mossy_cobblestone":3,"securitycraft:universal_block_remover":1,"butcher:rawcreepermeat":6,"butcher:sulfur":15,"minecraft:diamond":32,"waystones:waystone":1,"minecraft:rooted_dirt":3,"butcher:raw_lamb_sirloin":3,"minecraft:oak_sapling":10,"minecraft:netherrack":4,"butcher:liver":16,"minecraft:coarse_dirt":2,"minecraft:crafting_table":5,"butcher:spiderhead":1,"butcher:raw_lamb_shoulder":3,"minecraft:chicken":1,"butcher:rawlambloin":3,"meadow:fire_lily":14,"butcher:raw_sirloin_steak":2,"meadow:pine_fence":1,"minecraft:blackstone":13,"butcher:spidercarcass":2,"minecraft:beef":6,"vinery:cherry":3,"minecraft:chest":1,"minecraft:sugar_cane":12,"meadow:alpine_salt":9,"minecraft:birch_sapling":4,"butcher:creeperleg":4,"minecraft:egg":5,"butcher:lambrib":3,"minecraft:raw_iron":92,"tconstruct:raw_cobalt":4,"butcher:pighead":5,"butcher:spiderleg":6,"sophisticatedbackpacks:backpack":4,"butcher:sheep_corpse_item":5,"butcher:pillagerdisguise_boots":1,"minecraft:carrot":5,"minecraft:tnt":3,"minecraft:arrow":12,"botania:lime_mystical_flower":7,"tconstruct:tinker_station":1,"minecraft:hay_block":6,"butcher:rawcreeperleg":18,"butcher:raw_pork_loin":4,"minecraft:mutton":8,"minecraft:skeleton_skull":2,"minecraft:white_wool":7,"butcher:pillagerdisguise_chestplate":1,"meadow:limestone_slab":1,"minecraft:leather":7,"minecraft:oak_log":40,"minecraft:golden_boots":1,"minecraft:gunpowder":5,"meadow:pine_planks":1,"butcher:pillagerhead":3,"minecraft:apple":75,"minecraft:kelp":6,"meadow:pine_sapling":134,"meadow:eriophorum":38,"butcher:hook_block":8,"butcher:raw_chuck_steak":2,"butcher:sheephead":5,"minecraft:smooth_basalt":1,"minecraft:birch_boat":3,"minecraft:pumpkin":2,"minecraft:gravel":13,"butcher:raw_rump_steak":2,"minecraft:spruce_sapling":29,"botania:lime_mushroom":1,"minecraft:white_bed":3,"minecraft:spruce_log":166,"meadow:pine_log":106,"butcher:heart":13,"minecraft:spider_eye":6,"butcher:cowhoof":36,"butcher:zombiecorpse":17,"butcher:raw_leg_of_lamb":3,"minecraft:slime_ball":44,"botania:orange_mystical_flower":1,"minecraft:cherry_sapling":1,"butcher:lungs":16,"botania:brown_mystical_flower":2,"minecraft:coal":60},"minecraft:dropped":{"minecraft:birch_planks":4,"meadow:enzian":10,"minecraft:cooked_beef":2,"botania:red_mystical_flower":1,"minecraft:golden_pickaxe":2,"minecraft:orange_tulip":1,"butcher:hammer":1,"minecraft:dirt":1,"meadow:eriophorum":26,"minecraft:gravel":12,"minecraft:stone_axe":1,"botania:brown_mystical_flower":2,"minecraft:rotten_flesh":10,"minecraft:oak_planks":5,"minecraft:glowstone_dust":3,"minecraft:carrot":2,"patchouli:guide_book":1,"farmersdelight:rope":2,"minecraft:arrow":3,"meadow:pine_planks":1,"minecraft:stone_brick_stairs":1,"minecraft:netherrack":2,"botania:gray_mushroom":1,"minecraft:wheat_seeds":35,"tconstruct:flint_and_brick":1,"minecraft:stick":13,"botania:orange_petal":2,"minecraft:pumpkin":2,"minecraft:golden_hoe":1,"minecraft:furnace":2,"minecraft:kelp":6,"sophisticatedbackpacks:backpack":2,"meadow:fire_lily":12,"botania:cyan_mystical_flower":3,"meadow:alpine_salt":6,"minecraft:oak_sapling":1,"minecraft:spider_eye":2,"minecraft:birch_boat":3,"minecraft:wooden_pickaxe":1,"botania:lime_mystical_flower":7,"farmersdelight:tomato":1},"minecraft:crafted":{"butcher:bloodgratetank":1,"securitycraft:mine":3,"minecraft:oak_planks":152,"butcher:hammer":1,"minecraft:birch_boat":4,"minecraft:chain":4,"minecraft:stone":8,"securitycraft:keypad_item":1,"minecraft:diamond_shovel":1,"minecraft:heavy_weighted_pressure_plate":1,"minecraft:cooked_mutton":4,"minecraft:iron_bars":16,"minecraft:chest":9,"butcher:cookedstomach":4,"minecraft:cooked_porkchop":6,"vinery:grapevine_stem":4,"minecraft:diamond_axe":1,"vinery:dark_cherry_planks":20,"minecraft:crafting_table":5,"minecraft:spruce_planks":216,"minecraft:wooden_pickaxe":1,"minecraft:iron_helmet":1,"meadow:pine_fence":54,"minecraft:birch_planks":56,"meadow:pine_planks":348,"minecraft:wooden_hoe":1,"minecraft:book":1,"minecraft:iron_chestplate":1,"minecraft:paper":3,"minecraft:diamond_pickaxe":1,"minecraft:shield":3,"minecraft:stick":124,"butcher:cookedheart":2,"minecraft:iron_ingot":69,"minecraft:iron_pickaxe":2,"butcher:butchers_knife":2,"vinery:red_grape_seeds":5,"minecraft:shears":1,"tconstruct:pattern":3,"securitycraft:furnace_mine":1,"minecraft:iron_nugget":45,"minecraft:furnace":3,"minecraft:stone_button":8,"minecraft:bone_meal":81,"tconstruct:tinker_station":1,"minecraft:iron_axe":1,"butcher:bonebutchersknife":1,"minecraft:stone_pickaxe":1,"tconstruct:earth_congealed_slime":1,"minecraft:wheat":54,"minecraft:cooked_beef":3,"botania:lexicon":1,"minecraft:bucket":2,"minecraft:stone_axe":1,"butcher:cookedliver":6,"minecraft:bread":18,"minecraft:air":0,"butcher:leg_of_lamb":2,"butcher:cookedkidney":7,"botania:orange_petal":2,"butcher:hook":6,"minecraft:iron_leggings":1,"minecraft:white_bed":1,"minecraft:torch":60,"butcher:tbonesteak":1},"minecraft:custom":{"minecraft:interact_with_crafting_table":62,"minecraft:leave_game":4,"minecraft:time_since_death":21157,"minecraft:sprint_one_cm":635176,"minecraft:damage_blocked_by_shield":6000,"minecraft:drop":74,"minecraft:talked_to_villager":2,"minecraft:play_time":441056,"minecraft:deaths":14,"minecraft:jump":4623,"minecraft:walk_on_water_one_cm":49254,"minecraft:interact_with_furnace":84,"minecraft:interact_with_cartography_table":1,"minecraft:sleep_in_bed":15,"minecraft:waystone_activated":9,"minecraft:damage_dealt":14723,"minecraft:crouch_one_cm":25566,"minecraft:horse_one_cm":2452,"minecraft:mob_kills":77,"minecraft:climb_one_cm":4919,"minecraft:walk_one_cm":1062009,"minecraft:damage_dealt_absorbed":40,"minecraft:sneak_time":10299,"minecraft:walk_under_water_one_cm":47883,"minecraft:boat_one_cm":237441,"minecraft:interact_with_blast_furnace":2,"minecraft:total_world_time":441056,"minecraft:time_since_rest":13058,"minecraft:damage_taken":8781,"minecraft:swim_one_cm":85519,"minecraft:fly_one_cm":726594,"minecraft:open_chest":192,"minecraft:fall_one_cm":119526},"minecraft:broken":{"minecraft:golden_helmet":1,"minecraft:shield":2,"minecraft:iron_axe":1},"minecraft:used":{"butcher:heart":1,"butcher:cookedheart":2,"butcher:kidney":1,"butcher:skeletoncorpse":1,"butcher:pillagerhead":2,"minecraft:chest":10,"minecraft:shield":111,"farmersdelight:cabbage":2,"minecraft:creeper_head":2,"minecraft:rotten_flesh":12,"butcher:chicken_corpse_item":3,"minecraft:mutton":2,"securitycraft:keypad_item":2,"butcher:spidercarcass":1,"minecraft:carrot":5,"minecraft:tuff":8,"meadow:cobbled_limestone":14,"farmersdelight:tomato":5,"butcher:cow_headf":2,"butcher:pighead":1,"butcher:raw_pork_leg":3,"butcher:blood_liquid_bucket":2,"butcher:cookedstomach":4,"minecraft:furnace":6,"minecraft:oak_sapling":1,"minecraft:skeleton_skull":1,"minecraft:egg":2,"butcher:bloodgratetank":4,"butcher:rawlambloin":1,"minecraft:golden_boots":1,"butcher:creepercarcass":3,"butcher:stomach":1,"minecraft:stone_pickaxe":107,"meadow:pine_fence":20,"minecraft:wooden_pickaxe":56,"minecraft:diamond_axe":274,"securitycraft:universal_block_remover":1,"waystones:waystone":2,"minecraft:bread":18,"butcher:rawcreeperleg":2,"botania:yellow_double_flower":1,"minecraft:gravel":1,"securitycraft:mine":3,"minecraft:golden_helmet":1,"butcher:skinned_cow_corpse_item":3,"minecraft:chain":4,"butcher:tbonesteak":1,"minecraft:bone_meal":75,"minecraft:golden_pickaxe":10,"butcher:creeperleg":2,"tconstruct:earth_congealed_slime":1,"minecraft:iron_bars":14,"butcher:clothed_pillager_corpse":2,"minecraft:spruce_planks":16,"butcher:spiderleg":6,"minecraft:netherrack":2,"meadow:pine_sapling":9,"minecraft:torch":66,"minecraft:dirt":431,"butcher:sheep_corpse_item":6,"butcher:cowcorpseitem":3,"butcher:sheephead":2,"farmersdelight:rope":5,"butcher:bonebutchersknife":19,"minecraft:iron_axe":196,"butcher:drained_pig_corpse_item":3,"minecraft:rooted_dirt":1,"butcher:cookedkidney":7,"tconstruct:tinker_station":2,"vinery:grapevine_stem":2,"minecraft:smooth_basalt":1,"butcher:pillagercorpse":1,"minecraft:beef":1,"botania:lime_mushroom":1,"butcher:hook_block":4,"minecraft:cooked_beef":1,"farmersdelight:tomato_seeds":8,"minecraft:cobbled_deepslate":12,"minecraft:cherry_log":1,"vinery:red_grape":2,"minecraft:cooked_mutton":4,"butcher:chicken_drained_corpse_item":2,"minecraft:water_bucket":64,"butcher:leg_of_lamb":2,"butcher:butchers_knife":183,"minecraft:birch_boat":4,"meadow:pine_planks":102,"butcher:liver":7,"minecraft:crafting_table":9,"minecraft:white_bed":4,"securitycraft:furnace_mine":1,"butcher:pig_corpse_item":10,"minecraft:spruce_log":48,"minecraft:wooden_hoe":9,"minecraft:apple":24,"minecraft:diamond_pickaxe":61,"minecraft:diamond_shovel":418,"minecraft:iron_pickaxe":248,"minecraft:spruce_sapling":8,"butcher:zombiecorpse":13,"minecraft:stone_axe":21,"minecraft:cobblestone":98,"butcher:cookedliver":4,"minecraft:porkchop":15,"minecraft:cooked_porkchop":6,"minecraft:bucket":68,"vinery:apple_tree_sapling":1,"meadow:pine_log":19,"vinery:red_grape_seeds":8}},"DataVersion":3465}